uwg_schema/__init__.py
uwg_schema/_base.py
uwg_schema/_openapi.py
uwg_schema/model.py
uwg_schema/ref_bld_template.py
uwg_schema-0.2.11.dist-info/LICENSE
uwg_schema-0.2.11.dist-info/METADATA
uwg_schema-0.2.11.dist-info/WHEEL
uwg_schema-0.2.11.dist-info/top_level.txt
uwg_schema-0.2.11.dist-info/RECORD
