Metadata-Version: 2.1
Name: uwg-schema
Version: 0.2.11
Summary: Input schema for the Urban Weather Generator (UWG).
Home-page: https://github.com/ladybug-tools/uwg-schema
Author: Ladybug Tools
Author-email: info@ladybug.tools
License: UNKNOWN
Platform: UNKNOWN
Classifier: Programming Language :: Python :: 3.6
Classifier: Programming Language :: Python :: 3.7
Classifier: Programming Language :: Python :: Implementation :: CPython
Classifier: Operating System :: OS Independent
License-File: LICENSE
Requires-Dist: pydantic-openapi-helper (>=0.2.9)
